pyImpinj/ImpinjR2K.py
pyImpinj/__init__.py
pyImpinj/constant.py
pyImpinj/enums.py
pyImpinj/protocol.py
pyImpinj/test/auto_config.py
pyImpinj/test/case_read.py
pyImpinj/test/case_write.py
pyImpinj/test/inventory-fast.py
pyImpinj/test/inventory-rt.py
pyImpinj/test/inventory.py
pyImpinj-1.2.dist-info/LICENSE
pyImpinj-1.2.dist-info/METADATA
pyImpinj-1.2.dist-info/WHEEL
pyImpinj-1.2.dist-info/top_level.txt
pyImpinj-1.2.dist-info/RECORD
