Metadata-Version: 2.1
Name: pyImpinj
Version: 1.2
Summary: Library for Impinj R2000 Reader
Home-page: https://github.com/hex-in/pyImpinj
Author: Heyn
Author-email: heyunhuan@gmail.com
License: MIT
Keywords: Impinj,R2000
Platform: any
Classifier: Development Status :: 3 - Alpha
Classifier: Intended Audience :: Developers
Classifier: Topic :: Software Development :: Build Tools
Classifier: License :: OSI Approved :: MIT License
Classifier: Programming Language :: Python :: 3
Classifier: Programming Language :: Python :: 3.5
Classifier: Programming Language :: Python :: 3.6
Classifier: Programming Language :: Python :: 3.7
Classifier: Programming Language :: Python :: 3.8
Classifier: Programming Language :: Python :: Implementation :: CPython
Classifier: Programming Language :: Python :: Implementation :: PyPy
Requires-Dist: pyserial (>=3.4)
Requires-Dist: libscrc (==0.1.6)
